streamlit_mosaic/__init__.py
streamlit_mosaic/frontend/build/asset-manifest.json
streamlit_mosaic/frontend/build/index.html
streamlit_mosaic/frontend/build/static/js/main.ecb5e3b8.js
streamlit_mosaic/frontend/build/static/js/main.ecb5e3b8.js.LICENSE.txt
streamlit_mosaic/frontend/build/static/js/main.ecb5e3b8.js.map
streamlit_mosaic-0.0.2.dist-info/LICENSE
streamlit_mosaic-0.0.2.dist-info/METADATA
streamlit_mosaic-0.0.2.dist-info/WHEEL
streamlit_mosaic-0.0.2.dist-info/top_level.txt
streamlit_mosaic-0.0.2.dist-info/RECORD
