Metadata-Version: 2.1
Name: streamlit-mosaic
Version: 0.0.2
Summary: Mosaic for Streamlit
Home-page: https://github.com/ploomber/streamlit-mosaic
Author: Ploomber Inc.
Author-email: contact@ploomber.io
Requires-Python: >=3.6
License-File: LICENSE
Requires-Dist: streamlit >=0.63
